pymondis/__init__.py
pymondis/_client.py
pymondis/_enums.py
pymondis/_exceptions.py
pymondis/_http.py
pymondis/_metadata.py
pymondis/_models.py
pymondis/_util.py
pymondis-1.0.0a9.dist-info/LICENSE
pymondis-1.0.0a9.dist-info/METADATA
pymondis-1.0.0a9.dist-info/WHEEL
pymondis-1.0.0a9.dist-info/top_level.txt
pymondis-1.0.0a9.dist-info/RECORD
