Metadata-Version: 2.1
Name: pymondis
Version: 1.0.0a9
Summary: Nieoficjalny wrapper Quatromondis API
Home-page: https://github.com/Asapros/pymondis
Author: Asapros
License: MIT
Project-URL: Tracker, https://github.com/Asapros/pymondis/issues
Project-URL: Source, https://github.com/Asapros/pymondis
Keywords: quatromondis,yorck,API,HTTP,async,hugo
Platform: UNKNOWN
Classifier: Development Status :: 3 - Alpha
Classifier: Natural Language :: Polish
Classifier: Operating System :: OS Independent
Classifier: Programming Language :: Python :: 3.10
Classifier: Topic :: Software Development :: Libraries :: Python Modules
Classifier: Intended Audience :: Developers
Requires-Python: >=3.10
License-File: LICENSE
Requires-Dist: httpx (~=0.20.0)
Requires-Dist: attrs (~=21.2.0)
